[{"phase":"1","next":"读取 deep-research 策略并执行项目迁移评估","ts":1781019126982},{"phase":"1","next":"读取 deep-research 策略并执行项目迁移评估","ts":1781019468792},{"phase":"1","next":"读取 deep-research 策略并执行项目迁移评估","ts":1781019748436},{"phase":"1","next":"读取 deep-research 策略并执行项目迁移评估","ts":1781025180724},{"phase":"1","next":"读取 deep-research 策略并执行项目迁移评估","ts":1781025451188},{"phase":"1","next":"读取 deep-research 策略并执行项目迁移评估","ts":1781025642985},{"phase":"1","next":"读取 deep-research 策略并执行项目迁移评估","ts":1781025824201},{"phase":"1","next":"读取 deep-research 策略并执行项目迁移评估","ts":1781026032752},{"phase":"1","next":"读取 deep-research 策略并执行项目迁移评估","ts":1781026238341},{"phase":"1","next":"读取 deep-research 策略并执行项目迁移评估","ts":1781026870690}]